deskaone_script_sdk/BitcoinMining/__init__.py
deskaone_script_sdk/BitcoinMining/BitcoinMining.cp311-win_amd64.pyd
deskaone_script_sdk/BitcoinMining/BitcoinMining.cp312-win_amd64.pyd
deskaone_script_sdk/BitcoinMining/BitcoinMining.cp38-win32.pyd
deskaone_script_sdk/BitcoinMining/BitcoinMining.cp38-win_amd64.pyd
deskaone_script_sdk/BitcoinMining/BitcoinMining.cp39-win_amd64.pyd
deskaone_script_sdk/BitcoinMining/BitcoinMining.cpython-311.so
deskaone_script_sdk/BitcoinMining/BitcoinMining.cpython-312-x86_64-linux-gnu.so
deskaone_script_sdk/BProgrammers/__init__.py
deskaone_script_sdk/BProgrammers/BProgrammers.cp311-win_amd64.pyd
deskaone_script_sdk/BProgrammers/BProgrammers.cp312-win_amd64.pyd
deskaone_script_sdk/BProgrammers/BProgrammers.cp38-win32.pyd
deskaone_script_sdk/BProgrammers/BProgrammers.cp38-win_amd64.pyd
deskaone_script_sdk/BProgrammers/BProgrammers.cp39-win_amd64.pyd
deskaone_script_sdk/BProgrammers/BProgrammers.cpython-311.so
deskaone_script_sdk/BProgrammers/BProgrammers.cpython-312-x86_64-linux-gnu.so
deskaone_script_sdk/BProgrammers/Params.cp311-win_amd64.pyd
deskaone_script_sdk/BProgrammers/Params.cp312-win_amd64.pyd
deskaone_script_sdk/BProgrammers/Params.cp38-win32.pyd
deskaone_script_sdk/BProgrammers/Params.cp38-win_amd64.pyd
deskaone_script_sdk/BProgrammers/Params.cp39-win_amd64.pyd
deskaone_script_sdk/BProgrammers/Params.cpython-311.so
deskaone_script_sdk/BProgrammers/Params.cpython-312-x86_64-linux-gnu.so
deskaone_script_sdk/BProgrammers/Rpc.cp311-win_amd64.pyd
deskaone_script_sdk/BProgrammers/Rpc.cp312-win_amd64.pyd
deskaone_script_sdk/BProgrammers/Rpc.cp38-win32.pyd
deskaone_script_sdk/BProgrammers/Rpc.cp38-win_amd64.pyd
deskaone_script_sdk/BProgrammers/Rpc.cp39-win_amd64.pyd
deskaone_script_sdk/BProgrammers/Rpc.cpython-311.so
deskaone_script_sdk/BProgrammers/Rpc.cpython-312-x86_64-linux-gnu.so
deskaone_script_sdk/BProgrammers/Settings.cp311-win_amd64.pyd
deskaone_script_sdk/BProgrammers/Settings.cp312-win_amd64.pyd
tuyul_online_sdk_v2-0.1.0.dist-info/METADATA
tuyul_online_sdk_v2-0.1.0.dist-info/WHEEL
tuyul_online_sdk_v2-0.1.0.dist-info/RECORD
